doclifter/__init__.py
doclifter-2.20.4.data/data/share/man/man1/doclifter.1.gz
doclifter-2.20.4.data/scripts/doclifter
doclifter-2.20.4.dist-info/COPYING
doclifter-2.20.4.dist-info/METADATA
doclifter-2.20.4.dist-info/WHEEL
doclifter-2.20.4.dist-info/top_level.txt
doclifter-2.20.4.dist-info/RECORD
