Metadata-Version: 2.1
Name: doclifter
Version: 2.20.4
Summary: Lift documents in {n,t}roff markups to XML-DocBook.
Home-page: https://gitlab.com/esr/doclifter
Author: Eric S. Raymond
Author-email: esr@thyrsus.com
Maintainer: Mingzhe Zou
Maintainer-email: zoumingzhe@outlook.com
License-File: COPYING
